CHANGES.txt
LICENSE.txt
MANIFEST.in
README.rst
setup.py
configtreeview/__init__.py
configtreeview/configtreeview.py
configtreeview.egg-info/PKG-INFO
configtreeview.egg-info/SOURCES.txt
configtreeview.egg-info/dependency_links.txt
configtreeview.egg-info/requires.txt
configtreeview.egg-info/top_level.txt
configtreeview/tools/__init__.py
configtreeview/tools/dataformatter.py