Metadata-Version: 1.0
Name: configtreeview
Version: 0.1.32
Summary: An easily configurable GtkTreeView implementation for pygtk.
Home-page: http://github.com/wrhansen/ConfigTreeView
Author: Wesley Hansen
Author-email: wes@ridersdiscount.com
License: GPLv3
Platform: POSIX
Platform: Windows
